gpt_chat_cli/__init__.py
gpt_chat_cli/argparsing.py
gpt_chat_cli/chat_colorizer.py
gpt_chat_cli/color.py
gpt_chat_cli/gcli.py
gpt_chat_cli/openai_wrappers.py
gpt_chat_cli/streaming_lexer.py
gpt_chat_cli/version.py
gpt_chat_cli-0.1.2.dist-info/LICENSE
gpt_chat_cli-0.1.2.dist-info/METADATA
gpt_chat_cli-0.1.2.dist-info/WHEEL
gpt_chat_cli-0.1.2.dist-info/entry_points.txt
gpt_chat_cli-0.1.2.dist-info/top_level.txt
gpt_chat_cli-0.1.2.dist-info/RECORD
