Metadata-Version: 2.1
Name: gpt-chat-cli
Version: 0.1.2
Summary: A simple ChatGPT terminal CLI
Author: Flu0r1ne
Author-email: Flu0r1ne <flu0r1ne@flu0r1ne.net>
Project-URL: Homepage, https://github.com/flu0r1ne/gpt-chat-cli
Project-URL: Bug Tracker, https://github.com/flu0r1ne/gpt-chat-cli/issues
Classifier: Programming Language :: Python :: 3
Classifier: License :: OSI Approved :: MIT License
Classifier: Operating System :: OS Independent
Requires-Python: >=3.7
License-File: LICENSE
Requires-Dist: setuptools
Requires-Dist: openai (>=0.27.6)
Requires-Dist: pygments (>=0.15.0)
